{
    "id": "IazGP58LMR0",
    "slug": "a-sign-that-says-put-up-or-shut-up-IazGP58LMR0",
    "alternative_slugs": {
        "en": "a-sign-that-says-put-up-or-shut-up-IazGP58LMR0",
        "es": "un-letrero-que-dice-aguanta-o-callate-IazGP58LMR0",
        "ja": "\u6211\u6162\u3059\u308b\u304b\u9ed9\u308b\u304b\u306e\u770b\u677f-IazGP58LMR0",
        "fr": "une-pancarte-qui-dit-mets-en-place-ou-tais-toi-IazGP58LMR0",
        "it": "un-cartello-che-dice-alzati-o-stai-zitto-IazGP58LMR0",
        "ko": "put-up-or-shut-up\uc774\ub77c\ub294-\ud45c\uc9c0\ud310-IazGP58LMR0",
        "de": "ein-schild-auf-dem-steht-halt-die-klappe-IazGP58LMR0",
        "pt": "uma-placa-que-diz-colocar-ou-calar-a-boca-IazGP58LMR0"
    },
    "created_at": "2024-04-11T01:01:37Z",
    "updated_at": "2024-04-15T00:28:50Z",
    "promoted_at": "2024-04-12T11:24:14Z",
    "width": 5472,
    "height": 3078,
    "color": "#260c0c",
    "blur_hash": "L85z?woLWBofj[a|jtay0yWVofWC",
    "description": null,
    "alt_description": "a sign that says put up or shut up",
    "breadcrumbs": [],
    "urls": {
        "raw": "https://images.unsplash.com/photo-1712797229262-f20f799b0639?ixid=M3w1OTU2NTh8MHwxfHJhbmRvbXx8fHx8fHx8fDE3MTQ0MzM5MjZ8&ixlib=rb-4.0.3",
        "full": "https://images.unsplash.com/photo-1712797229262-f20f799b0639?crop=entropy&cs=srgb&fm=jpg&ixid=M3w1OTU2NTh8MHwxfHJhbmRvbXx8fHx8fHx8fDE3MTQ0MzM5MjZ8&ixlib=rb-4.0.3&q=85",
        "regular": "https://images.unsplash.com/photo-1712797229262-f20f799b0639?crop=entropy&cs=tinysrgb&fit=max&fm=jpg&ixid=M3w1OTU2NTh8MHwxfHJhbmRvbXx8fHx8fHx8fDE3MTQ0MzM5MjZ8&ixlib=rb-4.0.3&q=80&w=1080",
        "small": "https://images.unsplash.com/photo-1712797229262-f20f799b0639?crop=entropy&cs=tinysrgb&fit=max&fm=jpg&ixid=M3w1OTU2NTh8MHwxfHJhbmRvbXx8fHx8fHx8fDE3MTQ0MzM5MjZ8&ixlib=rb-4.0.3&q=80&w=400",
        "thumb": "https://images.unsplash.com/photo-1712797229262-f20f799b0639?crop=entropy&cs=tinysrgb&fit=max&fm=jpg&ixid=M3w1OTU2NTh8MHwxfHJhbmRvbXx8fHx8fHx8fDE3MTQ0MzM5MjZ8&ixlib=rb-4.0.3&q=80&w=200",
        "small_s3": "https://s3.us-west-2.amazonaws.com/images.unsplash.com/small/photo-1712797229262-f20f799b0639"
    },
    "links": {
        "self": "https://api.unsplash.com/photos/a-sign-that-says-put-up-or-shut-up-IazGP58LMR0",
        "html": "https://unsplash.com/photos/a-sign-that-says-put-up-or-shut-up-IazGP58LMR0",
        "download": "https://unsplash.com/photos/IazGP58LMR0/download?ixid=M3w1OTU2NTh8MHwxfHJhbmRvbXx8fHx8fHx8fDE3MTQ0MzM5MjZ8",
        "download_location": "https://api.unsplash.com/photos/IazGP58LMR0/download?ixid=M3w1OTU2NTh8MHwxfHJhbmRvbXx8fHx8fHx8fDE3MTQ0MzM5MjZ8"
    },
    "likes": 14,
    "liked_by_user": false,
    "current_user_collections": [],
    "sponsorship": null,
    "topic_submissions": {},
    "asset_type": "photo",
    "user": {
        "id": "Uneml_yNJZE",
        "updated_at": "2024-04-29T20:47:14Z",
        "username": "reganography",
        "name": "Samuel Regan-Asante",
        "first_name": "Samuel",
        "last_name": "Regan-Asante",
        "twitter_username": "fkaregan",
        "portfolio_url": null,
        "bio": "Former child.\r\nIf you'd like to donate for any photos please make a contribution to Prostate Cancer UK.  https://prostatecanceruk.org/get-involved/donate.  Thanks. ",
        "location": "London",
        "links": {
            "self": "https://api.unsplash.com/users/reganography",
            "html": "https://unsplash.com/@reganography",
            "photos": "https://api.unsplash.com/users/reganography/photos",
            "likes": "https://api.unsplash.com/users/reganography/likes",
            "portfolio": "https://api.unsplash.com/users/reganography/portfolio",
            "following": "https://api.unsplash.com/users/reganography/following",
            "followers": "https://api.unsplash.com/users/reganography/followers"
        },
        "profile_image": {
            "small": "https://images.unsplash.com/profile-fb-1525756603-79e579036b2d.jpg?ixlib=rb-4.0.3&crop=faces&fit=crop&w=32&h=32",
            "medium": "https://images.unsplash.com/profile-fb-1525756603-79e579036b2d.jpg?ixlib=rb-4.0.3&crop=faces&fit=crop&w=64&h=64",
            "large": "https://images.unsplash.com/profile-fb-1525756603-79e579036b2d.jpg?ixlib=rb-4.0.3&crop=faces&fit=crop&w=128&h=128"
        },
        "instagram_username": "reganography",
        "total_collections": 3,
        "total_likes": 404,
        "total_photos": 1302,
        "total_promoted_photos": 167,
        "total_illustrations": 0,
        "total_promoted_illustrations": 0,
        "accepted_tos": true,
        "for_hire": false,
        "social": {
            "instagram_username": "reganography",
            "portfolio_url": null,
            "twitter_username": "fkaregan",
            "paypal_email": null
        }
    },
    "exif": {
        "make": "SONY",
        "model": "DSC-RX100M7",
        "name": "SONY, DSC-RX100M7",
        "exposure_time": "1/320",
        "aperture": "2.8",
        "focal_length": "9.0",
        "iso": 200
    },
    "location": {
        "name": null,
        "city": null,
        "country": null,
        "position": {
            "latitude": 0.0,
            "longitude": 0.0
        }
    },
    "meta": {
        "index": true
    },
    "public_domain": false,
    "tags": [
        {
            "type": "search",
            "title": "mini golf"
        },
        {
            "type": "search",
            "title": "neon light"
        },
        {
            "type": "search",
            "title": "put up or shut up"
        },
        {
            "type": "search",
            "title": "putt up or shut up"
        },
        {
            "type": "search",
            "title": "lighting"
        },
        {
            "type": "landing_page",
            "title": "light",
            "source": {
                "ancestry": {
                    "type": {
                        "slug": "backgrounds",
                        "pretty_slug": "Backgrounds"
                    },
                    "category": {
                        "slug": "colors",
                        "pretty_slug": "Colors"
                    },
                    "subcategory": {
                        "slug": "light",
                        "pretty_slug": "Light"
                    }
                },
                "title": "Light backgrounds",
                "subtitle": "Download free light background images",
                "description": "Unsplash has an amazing collection of light backgrounds, covering all different shades and styles. Our images are professionally-shot, and you can use any/all of them for free!",
                "meta_title": "900+ Light Background Images: Download HD Backgrounds on Unsplash",
                "meta_description": "Choose from hundreds of free light backgrounds. Download beautiful, curated free backgrounds on Unsplash.",
                "cover_photo": {
                    "id": "2x19-mRQgX8",
                    "slug": "person-holding-string-lights-2x19-mRQgX8",
                    "alternative_slugs": {
                        "en": "person-holding-string-lights-2x19-mRQgX8",
                        "es": "persona-sosteniendo-guirnaldas-de-luces-2x19-mRQgX8",
                        "ja": "\u30b9\u30c8\u30ea\u30f3\u30b0\u30e9\u30a4\u30c8\u3092\u6301\u3063\u3066\u3044\u308b\u4eba-2x19-mRQgX8",
                        "fr": "personne-tenant-des-guirlandes-lumineuses-2x19-mRQgX8",
                        "it": "persona-che-tiene-le-luci-della-stringa-2x19-mRQgX8",
                        "ko": "\ub048-\uc870\uba85\uc744-\ub4e4\uace0-\uc788\ub294-\uc0ac\ub78c-2x19-mRQgX8",
                        "de": "person-mit-lichterkette-2x19-mRQgX8",
                        "pt": "pessoa-segurando-luzes-de-corda-2x19-mRQgX8"
                    },
                    "created_at": "2016-12-19T16:23:39Z",
                    "updated_at": "2024-04-22T16:44:43Z",
                    "promoted_at": "2016-12-19T16:23:39Z",
                    "width": 5760,
                    "height": 3840,
                    "color": "#26260c",
                    "blur_hash": "LB8g4=R-0#WB=_WWNHWCE2ay={kC",
                    "description": null,
                    "alt_description": "person holding string lights",
                    "breadcrumbs": [
                        {
                            "slug": "images",
                            "title": "1,000,000+ Free Images",
                            "index": 0,
                            "type": "landing_page"
                        },
                        {
                            "slug": "feelings",
                            "title": "Feelings Images",
                            "index": 1,
                            "type": "landing_page"
                        },
                        {
                            "slug": "beautiful",
                            "title": "Beautiful Pictures & Images",
                            "index": 2,
                            "type": "landing_page"
                        }
                    ],
                    "urls": {
                        "raw": "https://images.unsplash.com/photo-1482164565953-04b62dcac1cd?ixlib=rb-4.0.3",
                        "full": "https://images.unsplash.com/photo-1482164565953-04b62dcac1cd?ixlib=rb-4.0.3&q=85&fm=jpg&crop=entropy&cs=srgb",
                        "regular": "https://images.unsplash.com/photo-1482164565953-04b62dcac1cd?ixlib=rb-4.0.3&q=80&fm=jpg&crop=entropy&cs=tinysrgb&w=1080&fit=max",
                        "small": "https://images.unsplash.com/photo-1482164565953-04b62dcac1cd?ixlib=rb-4.0.3&q=80&fm=jpg&crop=entropy&cs=tinysrgb&w=400&fit=max",
                        "thumb": "https://images.unsplash.com/photo-1482164565953-04b62dcac1cd?ixlib=rb-4.0.3&q=80&fm=jpg&crop=entropy&cs=tinysrgb&w=200&fit=max",
                        "small_s3": "https://s3.us-west-2.amazonaws.com/images.unsplash.com/small/photo-1482164565953-04b62dcac1cd"
                    },
                    "links": {
                        "self": "https://api.unsplash.com/photos/person-holding-string-lights-2x19-mRQgX8",
                        "html": "https://unsplash.com/photos/person-holding-string-lights-2x19-mRQgX8",
                        "download": "https://unsplash.com/photos/2x19-mRQgX8/download",
                        "download_location": "https://api.unsplash.com/photos/2x19-mRQgX8/download"
                    },
                    "likes": 2327,
                    "liked_by_user": false,
                    "current_user_collections": [],
                    "sponsorship": null,
                    "topic_submissions": {
                        "spirituality": {
                            "status": "approved",
                            "approved_on": "2020-04-06T14:20:22Z"
                        }
                    },
                    "asset_type": "photo",
                    "premium": false,
                    "plus": false,
                    "user": {
                        "id": "eoa2PWCTCbk",
                        "updated_at": "2023-09-13T03:30:16Z",
                        "username": "joshboot",
                        "name": "Josh Boot",
                        "first_name": "Josh",
                        "last_name": "Boot",
                        "twitter_username": "joshboot_",
                        "portfolio_url": "http://www.creativedept.co.uk",
                        "bio": "Photographer & Film-Maker from Sheffield that loves capturing light & beauty.",
                        "location": "Sheffield",
                        "links": {
                            "self": "https://api.unsplash.com/users/joshboot",
                            "html": "https://unsplash.com/@joshboot",
                            "photos": "https://api.unsplash.com/users/joshboot/photos",
                            "likes": "https://api.unsplash.com/users/joshboot/likes",
                            "portfolio": "https://api.unsplash.com/users/joshboot/portfolio",
                            "following": "https://api.unsplash.com/users/joshboot/following",
                            "followers": "https://api.unsplash.com/users/joshboot/followers"
                        },
                        "profile_image": {
                            "small": "https://images.unsplash.com/profile-1456313839517-8fda35d2f1e5?ixlib=rb-4.0.3&crop=faces&fit=crop&w=32&h=32",
                            "medium": "https://images.unsplash.com/profile-1456313839517-8fda35d2f1e5?ixlib=rb-4.0.3&crop=faces&fit=crop&w=64&h=64",
                            "large": "https://images.unsplash.com/profile-1456313839517-8fda35d2f1e5?ixlib=rb-4.0.3&crop=faces&fit=crop&w=128&h=128"
                        },
                        "instagram_username": "joshboot",
                        "total_collections": 0,
                        "total_likes": 98,
                        "total_photos": 16,
                        "total_promoted_photos": 5,
                        "total_illustrations": 0,
                        "total_promoted_illustrations": 0,
                        "accepted_tos": true,
                        "for_hire": true,
                        "social": {
                            "instagram_username": "joshboot",
                            "portfolio_url": "http://www.creativedept.co.uk",
                            "twitter_username": "joshboot_",
                            "paypal_email": null
                        }
                    }
                }
            }
        },
        {
            "type": "search",
            "title": "outdoors"
        },
        {
            "type": "landing_page",
            "title": "nature",
            "source": {
                "ancestry": {
                    "type": {
                        "slug": "images",
                        "pretty_slug": "Images"
                    },
                    "category": {
                        "slug": "nature",
                        "pretty_slug": "Nature"
                    }
                },
                "title": "Nature images",
                "subtitle": "Download free nature images",
                "description": "Nature produces the most astoundingly beautiful images: the swirling lava of a volcano, palm trees against a blue sky, snow-capped mountains towering above. Unsplash has magnificent , high-quality photos of all the delights that nature has to offer.",
                "meta_title": "100+ Nature Pictures | Download Free Images & Stock Photos on Unsplash",
                "meta_description": "Choose from hundreds of free nature pictures. Download HD nature photos for free on Unsplash.",
                "cover_photo": {
                    "id": "VE5FRc7uiC4",
                    "slug": "star-in-space-VE5FRc7uiC4",
                    "alternative_slugs": {
                        "en": "star-in-space-VE5FRc7uiC4",
                        "es": "estrella-en-el-espacio-VE5FRc7uiC4",
                        "ja": "\u5b87\u5b99\u306e\u661f-VE5FRc7uiC4",
                        "fr": "etoile-dans-lespace-VE5FRc7uiC4",
                        "it": "stella-nello-spazio-VE5FRc7uiC4",
                        "ko": "\uc6b0\uc8fc\uc758-\ubcc4-VE5FRc7uiC4",
                        "de": "stern-im-weltraum-VE5FRc7uiC4",
                        "pt": "estrela-no-espaco-VE5FRc7uiC4"
                    },
                    "created_at": "2018-10-15T08:58:20Z",
                    "updated_at": "2024-04-03T16:54:05Z",
                    "promoted_at": "2018-10-15T12:23:00Z",
                    "width": 4640,
                    "height": 3480,
                    "color": "#262640",
                    "blur_hash": "L21o;CogI7WARNaxt9j]Mvaxxwof",
                    "description": "lost in the sky",
                    "alt_description": "star in space",
                    "breadcrumbs": [],
                    "urls": {
                        "raw": "https://images.unsplash.com/photo-1539593395743-7da5ee10ff07?ixlib=rb-4.0.3",
                        "full": "https://images.unsplash.com/photo-1539593395743-7da5ee10ff07?ixlib=rb-4.0.3&q=85&fm=jpg&crop=entropy&cs=srgb",
                        "regular": "https://images.unsplash.com/photo-1539593395743-7da5ee10ff07?ixlib=rb-4.0.3&q=80&fm=jpg&crop=entropy&cs=tinysrgb&w=1080&fit=max",
                        "small": "https://images.unsplash.com/photo-1539593395743-7da5ee10ff07?ixlib=rb-4.0.3&q=80&fm=jpg&crop=entropy&cs=tinysrgb&w=400&fit=max",
                        "thumb": "https://images.unsplash.com/photo-1539593395743-7da5ee10ff07?ixlib=rb-4.0.3&q=80&fm=jpg&crop=entropy&cs=tinysrgb&w=200&fit=max",
                        "small_s3": "https://s3.us-west-2.amazonaws.com/images.unsplash.com/small/photo-1539593395743-7da5ee10ff07"
                    },
                    "links": {
                        "self": "https://api.unsplash.com/photos/star-in-space-VE5FRc7uiC4",
                        "html": "https://unsplash.com/photos/star-in-space-VE5FRc7uiC4",
                        "download": "https://unsplash.com/photos/VE5FRc7uiC4/download",
                        "download_location": "https://api.unsplash.com/photos/VE5FRc7uiC4/download"
                    },
                    "likes": 126,
                    "liked_by_user": false,
                    "current_user_collections": [],
                    "sponsorship": null,
                    "topic_submissions": {
                        "nature": {
                            "status": "approved",
                            "approved_on": "2020-04-06T14:20:12Z"
                        }
                    },
                    "asset_type": "photo",
                    "premium": false,
                    "plus": false,
                    "user": {
                        "id": "PvaYY7qgvqU",
                        "updated_at": "2024-04-14T17:12:53Z",
                        "username": "akin",
                        "name": "Akin Cakiner",
                        "first_name": "Akin",
                        "last_name": "Cakiner",
                        "twitter_username": "pausyworld",
                        "portfolio_url": "https://akincakiner.com/",
                        "bio": "Get your beautiful photos featured on Instagram!\r\nCheck out my page @creatpix   Create the moment #creatpix ",
                        "location": "almelo",
                        "links": {
                            "self": "https://api.unsplash.com/users/akin",
                            "html": "https://unsplash.com/@akin",
                            "photos": "https://api.unsplash.com/users/akin/photos",
                            "likes": "https://api.unsplash.com/users/akin/likes",
                            "portfolio": "https://api.unsplash.com/users/akin/portfolio",
                            "following": "https://api.unsplash.com/users/akin/following",
                            "followers": "https://api.unsplash.com/users/akin/followers"
                        },
                        "profile_image": {
                            "small": "https://images.unsplash.com/profile-1655048539859-cd496ee39bd9image?ixlib=rb-4.0.3&crop=faces&fit=crop&w=32&h=32",
                            "medium": "https://images.unsplash.com/profile-1655048539859-cd496ee39bd9image?ixlib=rb-4.0.3&crop=faces&fit=crop&w=64&h=64",
                            "large": "https://images.unsplash.com/profile-1655048539859-cd496ee39bd9image?ixlib=rb-4.0.3&crop=faces&fit=crop&w=128&h=128"
                        },
                        "instagram_username": "akinvisualz",
                        "total_collections": 0,
                        "total_likes": 32,
                        "total_photos": 315,
                        "total_promoted_photos": 26,
                        "total_illustrations": 0,
                        "total_promoted_illustrations": 0,
                        "accepted_tos": true,
                        "for_hire": true,
                        "social": {
                            "instagram_username": "akinvisualz",
                            "portfolio_url": "https://akincakiner.com/",
                            "twitter_username": "pausyworld",
                            "paypal_email": null
                        }
                    }
                }
            }
        },
        {
            "type": "search",
            "title": "night"
        },
        {
            "type": "search",
            "title": "text"
        },
        {
            "type": "landing_page",
            "title": "fireworks",
            "source": {
                "ancestry": {
                    "type": {
                        "slug": "images",
                        "pretty_slug": "Images"
                    },
                    "category": {
                        "slug": "things",
                        "pretty_slug": "Things"
                    },
                    "subcategory": {
                        "slug": "fireworks",
                        "pretty_slug": "Fireworks"
                    }
                },
                "title": "Fireworks images & pictures",
                "subtitle": "Download free fireworks images",
                "description": "Choose from a curated selection of fireworks photos. Always free on Unsplash.",
                "meta_title": "500+ Fireworks Pictures | Download Free Images on Unsplash",
                "meta_description": "Choose from hundreds of free fireworks pictures. Download HD fireworks photos for free on Unsplash.",
                "cover_photo": {
                    "id": "xplrF8WMitE",
                    "slug": "fireworks-display-xplrF8WMitE",
                    "alternative_slugs": {
                        "en": "fireworks-display-xplrF8WMitE",
                        "es": "espectaculo-de-fuegos-artificiales-xplrF8WMitE",
                        "ja": "\u82b1\u706b-\u5927\u4f1a-xplrF8WMitE",
                        "fr": "artifice-xplrF8WMitE",
                        "it": "fuochi-d-artificio-xplrF8WMitE",
                        "ko": "\ubd88\uaf43\ub180\uc774-xplrF8WMitE",
                        "de": "feuerwerk-xplrF8WMitE",
                        "pt": "queima-de-fogos-xplrF8WMitE"
                    },
                    "created_at": "2019-02-03T11:47:16Z",
                    "updated_at": "2024-04-07T23:47:50Z",
                    "promoted_at": "2019-02-04T15:02:05Z",
                    "width": 3200,
                    "height": 4000,
                    "color": "#0c2626",
                    "blur_hash": "L36Q}167ITSgPA}t5kV@M{J7-Aof",
                    "description": null,
                    "alt_description": "fireworks display",
                    "breadcrumbs": [
                        {
                            "slug": "backgrounds",
                            "title": "HQ Background Images",
                            "index": 0,
                            "type": "landing_page"
                        },
                        {
                            "slug": "phone",
                            "title": "Phone Backgrounds",
                            "index": 1,
                            "type": "landing_page"
                        },
                        {
                            "slug": "iphone-xs-max",
                            "title": "iPhone XS Max Backgrounds",
                            "index": 2,
                            "type": "landing_page"
                        }
                    ],
                    "urls": {
                        "raw": "https://images.unsplash.com/photo-1549194400-06e6874c2fd1?ixlib=rb-4.0.3",
                        "full": "https://images.unsplash.com/photo-1549194400-06e6874c2fd1?ixlib=rb-4.0.3&q=85&fm=jpg&crop=entropy&cs=srgb",
                        "regular": "https://images.unsplash.com/photo-1549194400-06e6874c2fd1?ixlib=rb-4.0.3&q=80&fm=jpg&crop=entropy&cs=tinysrgb&w=1080&fit=max",
                        "small": "https://images.unsplash.com/photo-1549194400-06e6874c2fd1?ixlib=rb-4.0.3&q=80&fm=jpg&crop=entropy&cs=tinysrgb&w=400&fit=max",
                        "thumb": "https://images.unsplash.com/photo-1549194400-06e6874c2fd1?ixlib=rb-4.0.3&q=80&fm=jpg&crop=entropy&cs=tinysrgb&w=200&fit=max",
                        "small_s3": "https://s3.us-west-2.amazonaws.com/images.unsplash.com/small/photo-1549194400-06e6874c2fd1"
                    },
                    "links": {
                        "self": "https://api.unsplash.com/photos/fireworks-display-xplrF8WMitE",
                        "html": "https://unsplash.com/photos/fireworks-display-xplrF8WMitE",
                        "download": "https://unsplash.com/photos/xplrF8WMitE/download",
                        "download_location": "https://api.unsplash.com/photos/xplrF8WMitE/download"
                    },
                    "likes": 817,
                    "liked_by_user": false,
                    "current_user_collections": [],
                    "sponsorship": null,
                    "topic_submissions": {
                        "current-events": {
                            "status": "approved",
                            "approved_on": "2020-12-30T19:22:52Z"
                        }
                    },
                    "asset_type": "photo",
                    "premium": false,
                    "plus": false,
                    "user": {
                        "id": "tYaBQaEx3TI",
                        "updated_at": "2024-04-20T13:49:21Z",
                        "username": "kristian_lovstad",
                        "name": "Kristian L\u00f8vstad",
                        "first_name": "Kristian",
                        "last_name": "L\u00f8vstad",
                        "twitter_username": "lovstadkristian",
                        "portfolio_url": "http://kristianlovstad.com",
                        "bio": "Norwegian photographer",
                        "location": "Norway",
                        "links": {
                            "self": "https://api.unsplash.com/users/kristian_lovstad",
                            "html": "https://unsplash.com/@kristian_lovstad",
                            "photos": "https://api.unsplash.com/users/kristian_lovstad/photos",
                            "likes": "https://api.unsplash.com/users/kristian_lovstad/likes",
                            "portfolio": "https://api.unsplash.com/users/kristian_lovstad/portfolio",
                            "following": "https://api.unsplash.com/users/kristian_lovstad/following",
                            "followers": "https://api.unsplash.com/users/kristian_lovstad/followers"
                        },
                        "profile_image": {
                            "small": "https://images.unsplash.com/profile-1626369837831-82d49e474519?ixlib=rb-4.0.3&crop=faces&fit=crop&w=32&h=32",
                            "medium": "https://images.unsplash.com/profile-1626369837831-82d49e474519?ixlib=rb-4.0.3&crop=faces&fit=crop&w=64&h=64",
                            "large": "https://images.unsplash.com/profile-1626369837831-82d49e474519?ixlib=rb-4.0.3&crop=faces&fit=crop&w=128&h=128"
                        },
                        "instagram_username": "lovstadkristian",
                        "total_collections": 0,
                        "total_likes": 0,
                        "total_photos": 19,
                        "total_promoted_photos": 1,
                        "total_illustrations": 0,
                        "total_promoted_illustrations": 0,
                        "accepted_tos": true,
                        "for_hire": true,
                        "social": {
                            "instagram_username": "lovstadkristian",
                            "portfolio_url": "http://kristianlovstad.com",
                            "twitter_username": "lovstadkristian",
                            "paypal_email": null
                        }
                    }
                }
            }
        },
        {
            "type": "search",
            "title": "alphabet"
        },
        {
            "type": "search",
            "title": "symbol"
        },
        {
            "type": "search",
            "title": "ampersand"
        }
    ],
    "tags_preview": [
        {
            "type": "search",
            "title": "mini golf"
        },
        {
            "type": "search",
            "title": "neon light"
        },
        {
            "type": "search",
            "title": "put up or shut up"
        }
    ],
    "views": 133859,
    "downloads": 4551,
    "topics": []
}